lc_flask_reqparser/__init__.py
lc_flask_reqparser/request_parser.py
lc_flask_reqparser-0.1.3.dist-info/LICENSE
lc_flask_reqparser-0.1.3.dist-info/METADATA
lc_flask_reqparser-0.1.3.dist-info/WHEEL
lc_flask_reqparser-0.1.3.dist-info/top_level.txt
lc_flask_reqparser-0.1.3.dist-info/RECORD
