Metadata-Version: 2.1
Name: lc-flask-reqparser
Version: 0.1.3
Summary: UNKNOWN
Home-page: https://github.com/libcommon/flask-reqparser-py
Author: libcommon
Author-email: libcommon@protonmail.com
License: UNKNOWN
Project-URL: Issue Tracker, https://github.com/libcommon/flask-reqparser-py/issues
Project-URL: Releases, https://github.com/libcommon/flask-reqparser-py/releases
Platform: UNKNOWN
Classifier: Intended Audience :: Developers
Classifier: Programming Language :: Python :: 3
Classifier: License :: OSI Approved :: MIT License
Classifier: Operating System :: OS Independent
Requires-Python: >=3.6
Requires-Dist: Flask
